{
  "31bf1631-972e-56e1-9838-ded1c799356f": {
    "title": "Saipark",
    "subtitle": "West from Praise Coast",
    "areas": [
      {
        "area": "Fields",
        "rate": 95,
        "lumaRate": 4,
        "minSVs": 0,
        "eggMoves": 16,
        "temtemId": "96992559-d9cd-5674-9000-989efbced1ea"
      },
      {
        "area": "Hills",
        "rate": 100,
        "lumaRate": 4,
        "minSVs": 0,
        "eggMoves": 11,
        "temtemId": "f88b68cb-a120-53c7-b303-9dc19e517190"
      }
    ]
  }
}